exomaft/__init__.py
exomaft/exomaft.py
exomaft/getlines.py
exomaft/maft_combine.py
exomaft/maft_cross_correlation.py
exomaft/maft_feature_tracking.py
exomaft-1.0.0.dist-info/licenses/LICENSE
exomaft-1.0.0.dist-info/METADATA
exomaft-1.0.0.dist-info/WHEEL
exomaft-1.0.0.dist-info/top_level.txt
exomaft-1.0.0.dist-info/RECORD
