Metadata-Version: 2.4
Name: exomaft
Version: 1.0.0
License-File: LICENSE
Requires-Dist: numpy
Requires-Dist: matplotlib
Requires-Dist: pandas
Requires-Dist: scipy
Dynamic: license-file
